ez_setup.py
mcimage.py
setup.py
McImage.egg-info/PKG-INFO
McImage.egg-info/SOURCES.txt
McImage.egg-info/dependency_links.txt
McImage.egg-info/requires.txt
McImage.egg-info/top_level.txt
mcimage.egg-info/SOURCES.txt