Metadata-Version: 1.0
Name: McImage
Version: 1.1
Summary: Bulk image downloader command line tool
Home-page: UNKNOWN
Author: Darryl McClellan
Author-email: darryljm34@gmail.com
License: GNU GPL
Keywords: image download downloader picture pictures .jpg bulk automatic picture
Platform: UNKNOWN
